reddit_gen/__init__.py
reddit_gen/cli.py
reddit_gen/default_settings.py
reddit_gen/experimental.py
reddit_gen/generator.py
reddit_gen/handlers.py
reddit_gen/reddit_settings.py
reddit_gen/utils.py
reddit_gen-0.1.4.dist-info/entry_points.txt
reddit_gen-0.1.4.dist-info/LICENSE
reddit_gen-0.1.4.dist-info/WHEEL
reddit_gen-0.1.4.dist-info/METADATA
reddit_gen-0.1.4.dist-info/RECORD
