Metadata-Version: 2.1
Name: reddit-gen
Version: 0.1.4
Summary: Generate Reddit Accounts Automatically
License: MIT
Author: Mohammad Alyetama
Author-email: malyetama@pm.me
Requires-Python: >=3.7,<4.0
Classifier: License :: OSI Approved :: MIT License
Classifier: Programming Language :: Python :: 3
Classifier: Programming Language :: Python :: 3.10
Classifier: Programming Language :: Python :: 3.7
Classifier: Programming Language :: Python :: 3.8
Classifier: Programming Language :: Python :: 3.9
Requires-Dist: 2captcha-python (>=1.1.0)
Requires-Dist: beautifulsoup4 (>=4.10.0)
Requires-Dist: factory-boy (>=3.2.0)
Requires-Dist: loguru (>=0.6.0)
Requires-Dist: pymongo[srv] (>=4.1.1)
Requires-Dist: python-dotenv (>=0.17.1)
Requires-Dist: requests (>=2.26.0)
Requires-Dist: rich (>=10.6.0)
Requires-Dist: selenium (>=3.141.0)
Requires-Dist: tqdm (>=4.56.2)
